iscan/__init__.py
iscan/my_foci.R
iscan/score_estimator.py
iscan/shifted_edges.py
iscan/shifted_nodes.py
iscan/utils.py
iscan_dag-1.0.0.dist-info/LICENSE
iscan_dag-1.0.0.dist-info/METADATA
iscan_dag-1.0.0.dist-info/WHEEL
iscan_dag-1.0.0.dist-info/top_level.txt
iscan_dag-1.0.0.dist-info/RECORD
