Metadata-Version: 2.1
Name: iscan-dag
Version: 1.0.0
Summary: Implementation of the iSCAN algorithm for detecting distribution shifts
Author-email: Kevin Bello <kbello@cs.cmu.edu>, Tianyu Chen <tianyuchen@utexas.edu>
License: Apache 2.0
Project-URL: Repository, https://github.com/kevinsbello/iscan
Project-URL: Documentation, https://iscan-dag.readthedocs.io/en/latest/
Project-URL: Issues, https://github.com/kevinsbello/iscan/issues
Keywords: iscan,distribution shifts,causal mechanisms,bayesian networks,structure learning,difference network
Classifier: Programming Language :: Python :: 3
Classifier: License :: OSI Approved :: Apache Software License
Classifier: Operating System :: OS Independent
Classifier: Topic :: Scientific/Engineering :: Artificial Intelligence
Classifier: Intended Audience :: Science/Research
Classifier: Development Status :: 3 - Alpha
Requires-Python: >=3.6
License-File: LICENSE
Requires-Dist: numpy ~=1.24
Requires-Dist: scikit-learn ~=1.2
Requires-Dist: torch ~=2.0
Requires-Dist: igraph ~=0.10
Requires-Dist: GPy ~=1.10
Requires-Dist: kneed ~=0.8
Requires-Dist: pandas ~=2.0
Requires-Dist: rpy2 ~=3.5
Requires-Dist: matplotlib ~=3.7
